petty/__init__.py
petty/base64.py
petty/cli.py
petty/console.py
petty/debug.py
petty/decrypt.py
petty/hash.py
petty/hex.py
petty/net.py
petty/timeout.py
petty/zip.py
petty-0.1.1.dist-info/LICENSE
petty-0.1.1.dist-info/METADATA
petty-0.1.1.dist-info/WHEEL
petty-0.1.1.dist-info/entry_points.txt
petty-0.1.1.dist-info/top_level.txt
petty-0.1.1.dist-info/RECORD
